adminx/__init__.py
adminx/adminx.py
adminx/apps.py
adminx/filters.py
adminx/forms.py
adminx/layout.py
adminx/models.py
adminx/sites.py
adminx/util.py
adminx/vendors.py
adminx/widgets.py
adminx/migrations/0001_initial.py
adminx/migrations/0002_log.py
adminx/migrations/0003_auto_20160715_0100.py
adminx/migrations/__init__.py
adminx/plugins/__init__.py
adminx/plugins/actions.py
adminx/plugins/aggregation.py
adminx/plugins/ajax.py
adminx/plugins/auth.py
adminx/plugins/batch.py
adminx/plugins/bookmark.py
adminx/plugins/chart.py
adminx/plugins/comments.py
adminx/plugins/details.py
adminx/plugins/editable.py
adminx/plugins/export.py
adminx/plugins/filters.py
adminx/plugins/images.py
adminx/plugins/importexport.py
adminx/plugins/inline.py
adminx/plugins/language.py
adminx/plugins/layout.py
adminx/plugins/mobile.py
adminx/plugins/multiselect.py
adminx/plugins/passwords.py
adminx/plugins/portal.py
adminx/plugins/quickfilter.py
adminx/plugins/quickform.py
adminx/plugins/refresh.py
adminx/plugins/relate.py
adminx/plugins/relfield.py
adminx/plugins/sitemenu.py
adminx/plugins/sortablelist.py
adminx/plugins/themes.py
adminx/plugins/topnav.py
adminx/plugins/utils.py
adminx/plugins/wizard.py
adminx/plugins/xversion.py
adminx/templatetags/__init__.py
adminx/templatetags/xadmin_tags.py
adminx/views/__init__.py
adminx/views/base.py
adminx/views/dashboard.py
adminx/views/delete.py
adminx/views/detail.py
adminx/views/edit.py
adminx/views/form.py
adminx/views/list.py
adminx/views/website.py
django_adminx-2.0.3.dist-info/METADATA
django_adminx-2.0.3.dist-info/RECORD
django_adminx-2.0.3.dist-info/WHEEL
django_adminx-2.0.3.dist-info/top_level.txt
xadmin/__init__.py
xadmin/adminx.py
xadmin/apps.py
xadmin/filters.py
xadmin/forms.py
xadmin/layout.py
xadmin/models.py
xadmin/sites.py
xadmin/util.py
xadmin/vendors.py
xadmin/widgets.py
xadmin/migrations/0001_initial.py
xadmin/migrations/0002_log.py
xadmin/migrations/0003_auto_20160715_0100.py
xadmin/migrations/__init__.py
xadmin/plugins/__init__.py
xadmin/plugins/actions.py
xadmin/plugins/aggregation.py
